lcviz/__init__.py
lcviz/conftest.py
lcviz/events.py
lcviz/helper.py
lcviz/lcviz_style.vue
lcviz/marks.py
lcviz/state.py
lcviz/tools.py
lcviz/utils.py
lcviz/version.py
lcviz/viewers.py
lcviz/components/__init__.py
lcviz/components/components.py
lcviz/components/plugin_ephemeris_select.vue
lcviz/data/HAT-P-11_Kepler_Q0_snippet.fits
lcviz/data/README.rst
lcviz/data/icons/viewer_clone.svg
lcviz/loaders/__init__.py
lcviz/loaders/importers/__init__.py
lcviz/loaders/importers/to_dc_with_label.vue
lcviz/loaders/importers/lightcurve/__init__.py
lcviz/loaders/importers/lightcurve/lightcurve.py
lcviz/loaders/importers/lightcurve/lightcurve.vue
lcviz/loaders/importers/tpf/__init__.py
lcviz/loaders/importers/tpf/tpf.py
lcviz/loaders/parsers/__init__.py
lcviz/loaders/parsers/lightkurve.py
lcviz/plugins/__init__.py
lcviz/plugins/binning/__init__.py
lcviz/plugins/binning/binning.py
lcviz/plugins/binning/binning.vue
lcviz/plugins/coords_info/__init__.py
lcviz/plugins/coords_info/coords_info.py
lcviz/plugins/ephemeris/__init__.py
lcviz/plugins/ephemeris/ephemeris.py
lcviz/plugins/ephemeris/ephemeris.vue
lcviz/plugins/export/__init__.py
lcviz/plugins/export/export.py
lcviz/plugins/flatten/__init__.py
lcviz/plugins/flatten/flatten.py
lcviz/plugins/flatten/flatten.vue
lcviz/plugins/flux_column/__init__.py
lcviz/plugins/flux_column/flux_column.py
lcviz/plugins/flux_column/flux_column.vue
lcviz/plugins/frequency_analysis/__init__.py
lcviz/plugins/frequency_analysis/frequency_analysis.py
lcviz/plugins/frequency_analysis/frequency_analysis.vue
lcviz/plugins/markers/__init__.py
lcviz/plugins/markers/markers.py
lcviz/plugins/metadata_viewer/__init__.py
lcviz/plugins/metadata_viewer/metadata_viewer.py
lcviz/plugins/plot_options/__init__.py
lcviz/plugins/plot_options/plot_options.py
lcviz/plugins/stitch/__init__.py
lcviz/plugins/stitch/stitch.py
lcviz/plugins/stitch/stitch.vue
lcviz/plugins/subset_tools/__init__.py
lcviz/plugins/subset_tools/subset_tools.py
lcviz-1.2.1.dist-info/licenses/LICENSE.rst
lcviz-1.2.1.dist-info/METADATA
lcviz-1.2.1.dist-info/WHEEL
lcviz-1.2.1.dist-info/top_level.txt
lcviz-1.2.1.dist-info/RECORD
