Metadata-Version: 2.4
Name: lcviz
Version: 1.2.1
Summary: A Jdaviz-based light curve analysis and visualization tool
Author-email: JDADF Developers <kconroy@stsci.edu>
License: BSD 3-Clause License
Project-URL: Homepage, https://github.com/spacetelescope/lcviz
Keywords: astronomy,astrophysics
Classifier: Intended Audience :: Science/Research
Classifier: License :: OSI Approved :: BSD License
Classifier: Operating System :: OS Independent
Classifier: Programming Language :: Python :: 3
Classifier: Programming Language :: Python :: Implementation :: CPython
Classifier: Topic :: Scientific/Engineering :: Astronomy
Classifier: Topic :: Scientific/Engineering :: Physics
Requires-Python: >=3.11
License-File: LICENSE.rst
Requires-Dist: astropy>=5.2
Requires-Dist: jdaviz<4.5,>=4.4.1
Requires-Dist: lightkurve>=2.5.1
Requires-Dist: glue-jupyter>=0.22.2
Provides-Extra: test
Requires-Dist: pytest; extra == "test"
Requires-Dist: pytest-astropy; extra == "test"
Requires-Dist: pytest-tornasync; extra == "test"
Provides-Extra: docs
Requires-Dist: sphinx-astropy[confv2]>=1.9.1; extra == "docs"
Requires-Dist: sphinx_design; extra == "docs"
Requires-Dist: sphinx-togglebutton; extra == "docs"
Dynamic: license-file
